swagger_client/__init__.py
swagger_client/api_client.py
swagger_client/configuration.py
swagger_client/rest.py
swagger_client/api/__init__.py
swagger_client/api/basic_error_controller_api.py
swagger_client/api/event_sink_controller_api.py
swagger_client/api/health_controller_api.py
swagger_client/models/__init__.py
swagger_client/models/additional_data.py
swagger_client/models/event_bean.py
swagger_client/models/model_and_view.py
swagger_client/models/monitoring_context.py
swagger_client/models/report_monitor_info.py
swagger_client/models/response_entity.py
swagger_client/models/validation_result.py
swagger_client/models/view.py
test/__init__.py
test/test_additional_data.py
test/test_basic_error_controller_api.py
test/test_event_bean.py
test/test_event_sink_controller_api.py
test/test_health_controller_api.py
test/test_model_and_view.py
test/test_monitoring_context.py
test/test_report_monitor_info.py
test/test_response_entity.py
test/test_validation_result.py
test/test_view.py
eventsinksdkapi_swagger_client-1.0.3.dist-info/METADATA
eventsinksdkapi_swagger_client-1.0.3.dist-info/WHEEL
eventsinksdkapi_swagger_client-1.0.3.dist-info/top_level.txt
eventsinksdkapi_swagger_client-1.0.3.dist-info/RECORD
